cagmon/__init__.py
cagmon/agrement.py
cagmon/conchord.py
cagmon/echo.py
cagmon/main.py
cagmon/melody.py
CAGMon-0.8.5.dist-info/LICENSE
CAGMon-0.8.5.dist-info/METADATA
CAGMon-0.8.5.dist-info/WHEEL
CAGMon-0.8.5.dist-info/entry_points.txt
CAGMon-0.8.5.dist-info/top_level.txt
CAGMon-0.8.5.dist-info/RECORD
