Metadata-Version: 2.1
Name: CAGMon
Version: 0.8.5
Summary: Correlation Analysis based on Glitch Monitoring
Home-page: https://github.com/pjjung/cagmon
Author: Phil Jung
Author-email: pjjung@nims.re.kr
License: UNKNOWN
Platform: UNKNOWN
Classifier: Programming Language :: Python :: 2.7
Classifier: License :: OSI Approved :: GNU Lesser General Public License v3 or later (LGPLv3+)
Classifier: Operating System :: OS Independent
Requires-Python: >=2.7
Requires-Dist: gwpy (>=1.0.1)
Requires-Dist: lalsuite (>=1.4.4)
Requires-Dist: minepy (>=1.2.5)
Requires-Dist: setuptools
